cloud_storage_utility/__init__.py
cloud_storage_utility/csutil_cli.py
cloud_storage_utility/file_broker.py
cloud_storage_utility/common/__init__.py
cloud_storage_utility/common/base_cloud_storage.py
cloud_storage_utility/common/cloud_local_map.py
cloud_storage_utility/common/util.py
cloud_storage_utility/config/__init__.py
cloud_storage_utility/config/config.py
cloud_storage_utility/platforms/__init__.py
cloud_storage_utility/platforms/ibm_cloud_storage.py
cloud_storage_utility/types/__init__.py
cloud_storage_utility/types/bucket_key.py
cloud_storage_utility/types/ibm_configuration.py
cloud_storage_utility-0.0.1a12.data/scripts/csutil
cloud_storage_utility-0.0.1a12.dist-info/LICENSE.md
cloud_storage_utility-0.0.1a12.dist-info/METADATA
cloud_storage_utility-0.0.1a12.dist-info/WHEEL
cloud_storage_utility-0.0.1a12.dist-info/top_level.txt
cloud_storage_utility-0.0.1a12.dist-info/RECORD
