Metadata-Version: 2.1
Name: cloud-storage-utility
Version: 0.0.1a12
Summary: A multi-platform cloud storage utility
Home-page: https://github.com/AAInternal/cloud-storage-utility
Author: Nick Kahlor
Author-email: nkahlor@gmail.com
License: UNKNOWN
Platform: UNKNOWN
Classifier: Programming Language :: Python :: 3
Classifier: Programming Language :: Python :: 3.6
Classifier: Programming Language :: Python :: 3.7
Classifier: Programming Language :: Python :: 3.8
Classifier: Programming Language :: Python :: 3.9
Classifier: License :: OSI Approved :: MIT License
Classifier: Operating System :: OS Independent
Requires-Python: >=3.6
License-File: LICENSE.md
Requires-Dist: click
Requires-Dist: python-dotenv
Requires-Dist: aiohttp
Requires-Dist: xmltodict
Requires-Dist: tqdm
Requires-Dist: colorama
Requires-Dist: setuptools-scm
